CHANGES.txt
MANIFEST.in
README.txt
setup.cfg
setup.py
gp.bootstrap.egg-info/PKG-INFO
gp.bootstrap.egg-info/SOURCES.txt
gp.bootstrap.egg-info/dependency_links.txt
gp.bootstrap.egg-info/entry_points.txt
gp.bootstrap.egg-info/requires.txt
gp.bootstrap.egg-info/top_level.txt
gp.bootstrap.egg-info/zip-safe
gpbootstrap/__init__.py