Metadata-Version: 1.1
Name: gp.bootstrap
Version: 0.3
Summary: Small script to deal with zc.buildout bootstrapping
Home-page: UNKNOWN
Author: Gael Pasgrimaud
Author-email: gael@gawel.org
License: MIT
Platform: UNKNOWN
Classifier: Intended Audience :: Developers
Classifier: License :: OSI Approved :: MIT License
Classifier: Topic :: Internet :: WWW/HTTP :: WSGI :: Application
Classifier: Operating System :: POSIX
